Step 1:
Compiled from "Test.java"                                                                 
public class Test {                                                                       
  public Test();                                                                          
    Code:                                                                                 
       0: aload_0                                                                         
       1: invokespecial #1                  // Method java/lang/Object."<init>":()V       
       4: return                                                                          
                                                                                          
    Code:
       0: iconst_3
       1: istore_1
       2: iconst_4
       3: istore_2
       4: iconst_5
       5: istore_3
       6: iload_1
       7: iload_2
       8: iload_3
       9: imul
      10: iadd
      11: istore        4
      13: return
}

Step 2:
0: getstatic     #2                  // Field java/lang/System.out:Ljava/io/PrintStream;
       3: bipush        42
       5: invokevirtual #3                  // Method java/io/PrintStream.println:(I)V
       8: return

Parameter type is encoded as I for integer.
Return type is encoded as V for variable.
Parameters are loaded in the stack.